{ "version": "1.0", "resource": "$default", "path": "/", "httpMethod": "GET", "headers": { "Content-Length": "0", "Host": "www.hex7.com", "User-Agent": "REDACTED", "X-Amzn-Trace-Id": "Root=1-65b3ee6d-6fbbd3b653f87a394302cbbd", "X-Forwarded-For": "1.1.1.1", "X-Forwarded-Port": "443", "X-Forwarded-Proto": "https", "accept": "text/html,application/xhtml+xml,application/xml;q=0.9,image/avif,image/webp,*/*;q=0.8", "accept-encoding": "gzip, deflate, br", "accept-language": "en-US,en;q=0.5", "dnt": "1", "sec-fetch-dest": "document", "sec-fetch-mode": "navigate", "sec-fetch-site": "none", "sec-fetch-user": "?1", "sec-gpc": "1", "upgrade-insecure-requests": "1" }, "multiValueHeaders": { "Content-Length": [ "0" ], "Host": [ "www.hex7.com" ], "User-Agent": [ "REDACTED" ], "X-Amzn-Trace-Id": [ "Root=1-65b3ee6d-6fbbd3b653f87a394302cbbd" ], "X-Forwarded-For": [ "1.1.1.1" ], "X-Forwarded-Port": [ "443" ], "X-Forwarded-Proto": [ "https" ], "accept": [ "text/html,application/xhtml+xml,application/xml;q=0.9,image/avif,image/webp,*/*;q=0.8" ], "accept-encoding": [ "gzip, deflate, br" ], "accept-language": [ "en-US,en;q=0.5" ], "dnt": [ "1" ], "sec-fetch-dest": [ "document" ], "sec-fetch-mode": [ "navigate" ], "sec-fetch-site": [ "none" ], "sec-fetch-user": [ "?1" ], "sec-gpc": [ "1" ], "upgrade-insecure-requests": [ "1" ] }, "queryStringParameters": null, "multiValueQueryStringParameters": null, "requestContext": { "accountId": "REDACTED", "apiId": "s3bnaiep1k", "domainName": "www.hex7.com", "domainPrefix": "www", "extendedRequestId": "SKIxMg-kIAMEVMQ=", "httpMethod": "GET", "identity": { "accessKey": null, "accountId": null, "caller": null, "cognitoAmr": null, "cognitoAuthenticationProvider": null, "cognitoAuthenticationType": null, "cognitoIdentityId": null, "cognitoIdentityPoolId": null, "principalOrgId": null, "sourceIp": "1.1.1.1", "user": null, "userAgent": "REDACTED", "userArn": null }, "path": "/hex7/", "protocol": "HTTP/1.1", "requestId": "SKIxMg-kIAMEVMQ=", "requestTime": "26/Jan/2024:17:39:57 +0000", "requestTimeEpoch": 1706290797769, "resourceId": "$default", "resourcePath": "$default", "stage": "hex7" }, "pathParameters": null, "stageVariables": null, "body": null, "isBase64Encoded": false }
